{"cameraMode":{"drawMode":0,"name":"Shaded","section":"Shading Mode"},"sceneLighting":true,"audioPlay":false,"sceneViewState":{"m_AlwaysRefresh":false,"showFog":true,"showSkybox":true,"showFlares":true,"showImageEffects":true,"showParticleSystems":true,"showVisualEffectGraphs":true,"m_FxEnabled":true},"in2DMode":false,"pivot":{"x":25.51000213623047,"y":8.260000228881836,"z":0.23999349772930146},"rotation":{"x":0.14380985498428346,"y":-0.00297328969463706,"z":0.00043375283712521195,"w":0.9896080493927002},"size":10.0,"orthographic":false}